README.md
setup.cfg
setup.py
tfcf/__init__.py
tfcf/config.py
tfcf/metrics.py
tfcf.egg-info/PKG-INFO
tfcf.egg-info/SOURCES.txt
tfcf.egg-info/dependency_links.txt
tfcf.egg-info/requires.txt
tfcf.egg-info/top_level.txt
tfcf/datasets/__init__.py
tfcf/datasets/ml100k.py
tfcf/datasets/ml1m.py
tfcf/models/__init__.py
tfcf/models/model_base.py
tfcf/models/svd.py
tfcf/models/svdpp.py
tfcf/utils/__init__.py
tfcf/utils/data_utils.py